tracklist_downloader/__init__.py
tracklist_downloader/helpers.py
tracklist_downloader/main.py
tracklist_downloader/modules/__init__.py
tracklist_downloader/modules/config_validator.py
tracklist_downloader/modules/downloader.py
tracklist_downloader/modules/existing_download_checker.py
tracklist_downloader/modules/logging_module.py
tracklist_downloader/modules/post_download_cleaner.py
tracklist_downloader/spotify_token_retriever.py
tracklist_downloader-0.2.0.dist-info/entry_points.txt
tracklist_downloader-0.2.0.dist-info/METADATA
tracklist_downloader-0.2.0.dist-info/WHEEL
tracklist_downloader-0.2.0.dist-info/RECORD
