Metadata-Version: 2.1
Name: tracklist-downloader
Version: 0.2.0
Summary: 
Author: attila szuts
Author-email: 45080765+attilaszuts@users.noreply.github.com
Requires-Python: >=3.9.13,<3.12
Classifier: Programming Language :: Python :: 3
Classifier: Programming Language :: Python :: 3.10
Classifier: Programming Language :: Python :: 3.11
Requires-Dist: click (>=8.1.7,<9.0.0)
Requires-Dist: python-dotenv (>=1.0.0,<2.0.0)
Requires-Dist: spotdl (>=4.2.1,<5.0.0)
Requires-Dist: spotipy (>=2.23.0,<3.0.0)
Requires-Dist: validators (>=0.22.0,<0.23.0)
